aikicore/__init__.py
aikicore/activity.py
aikicore/constants.py
aikicore/containers.py
aikicore/domain.py
aikicore/error.py
aikicore/errors.py
aikicore/routing.py
aikicore/config/__init__.py
aikicore/config/json.py
aikicore/config/yaml.py
aikicore/objects/__init__.py
aikicore/objects/data.py
aikicore/objects/object.py
aikicore-0.2.4.dist-info/LICENSE
aikicore-0.2.4.dist-info/METADATA
aikicore-0.2.4.dist-info/WHEEL
aikicore-0.2.4.dist-info/top_level.txt
aikicore-0.2.4.dist-info/RECORD
