Metadata-Version: 2.1
Name: aikicore
Version: 0.2.4
Summary: The Core Library for the Spirit of Harmony
Home-page: https://github.com/greatstrength/aikicore
Download-URL: https://github.com/greatstrength/aikicore
Author: Andrew Shatz
Author-email: andrew@greatstrength.me
License: BSD 3
License-File: LICENSE
Requires-Dist: schematics >=2.1.1
Requires-Dist: pyyaml >=6.0.1
